{"type": "Feature", "id": 12523213, "geometry": {"type": "Point", "coordinates": [160.822723, -9.86376]}, "properties": {"woe:id": 12523213, "woe:parent_id": 1020499, "woe:name": "Marau Airport", "woe:placetype": 14, "woe:placetype_name": "Airport", "woe:lang": "ENG", "iso:country": "SB", "meta:provider": ["geoplanet:7.3.1", "geoplanet:7.3.2", "geoplanet:7.4.0", "geoplanet:7.4.1", "geoplanet:7.5.1", "geoplanet:7.5.2", "geoplanet:7.6.0", "geoplanet:7.8.1", "geoplanet:7.9.0", "geoplanet:7.10.0", "geoplanet:8.0.0", "woeplanet:8.0.0"], "meta:indexed": "2020-08-20T21:03:14.515317", "woe:alias_ENG_V": ["RUS Airport", "RUS"], "meta:updated": "2020-10-14T11:24:23.993148", "woe:hierarchy": {"continent": 24865674, "country": 23424766, "town": 0, "planet": 1, "county": 0, "suburb": 0, "state": 2344839, "region": 0, "localadmin": 0}, "woe:timezone_id": 28350947, "woe:hash": "rw4rgs7e3jcg", "woe:centroid": [160.822723, -9.86376], "geom:latitude": -9.86376, "geom:longitude": 160.822723, "geom:hash": "rw4rgs7e3jcg", "woe:latitude": -9.86376, "geom:centroid": [160.822723, -9.86376], "woe:longitude": 160.822723, "woe:repo": "woeplanet-airport-sb", "geom:area": 0.0, "woe:scale": 19}}